CHANGELOG.rst
LICENSE
MANIFEST.in
README.rst
requirements.txt
setup.py
TwitterSearch/TwitterOrder.py
TwitterSearch/TwitterSearch.py
TwitterSearch/TwitterSearchException.py
TwitterSearch/TwitterSearchOrder.py
TwitterSearch/TwitterUserOrder.py
TwitterSearch/__init__.py
TwitterSearch/utils.py
TwitterSearch.egg-info/PKG-INFO
TwitterSearch.egg-info/SOURCES.txt
TwitterSearch.egg-info/dependency_links.txt
TwitterSearch.egg-info/not-zip-safe
TwitterSearch.egg-info/requires.txt
TwitterSearch.egg-info/top_level.txt