Metadata-Version: 1.1
Name: TwitterSearch
Version: 1.0.2
Summary: A library to easily iterate tweets found by the Twitter API
Home-page: http://github.com/ckoepp/TwitterSearch
Author: Christian Koepp
Author-email: christian.koepp@tum.de
License: MIT
Keywords: twitter api search
Platform: UNKNOWN
Classifier: Programming Language :: Python
Classifier: Programming Language :: Python :: 2
Classifier: Programming Language :: Python :: 2.7
Classifier: Programming Language :: Python :: 3
Classifier: Programming Language :: Python :: 3.3
Classifier: Programming Language :: Python :: 3.4
Classifier: Development Status :: 5 - Production/Stable
Classifier: Intended Audience :: Science/Research
Classifier: Operating System :: OS Independent
Classifier: License :: OSI Approved :: MIT License
Classifier: Topic :: Internet :: WWW/HTTP :: Dynamic Content :: CGI Tools/Libraries
